bloxlink/__init__.py
bloxlink/exceptions.py
bloxlink.py-0.0.2.dist-info/LICENSE
bloxlink.py-0.0.2.dist-info/METADATA
bloxlink.py-0.0.2.dist-info/WHEEL
bloxlink.py-0.0.2.dist-info/top_level.txt
bloxlink.py-0.0.2.dist-info/RECORD
