Metadata-Version: 2.1
Name: bloxlink.py
Version: 0.0.2
Summary: Bloxlink.py is a lightweight wrapper for the [Bloxlink](https://blox.link) API.
Author-email: Redacted_Nac <nacinkc08@gmail.com>
License: MIT License
Project-URL: Bug Reports, https://github.com/Redacted-Nac/bloxlink.py/issues
Project-URL: Source, https://github.com/Redacted-Nac/bloxlink.py/
Keywords: bloxlink,roblox,discord
Requires-Python: >=3.9
License-File: LICENSE
Requires-Dist: requests
